arch_wiki_search/__init__.py
arch_wiki_search/cachingproxy.py
arch_wiki_search/converters.py
arch_wiki_search/core.py
arch_wiki_search/exchange.py
arch_wiki_search/iconqt.py
arch_wiki_search/icontxt.py
arch_wiki_search/run.py
arch_wiki_search/wikis.py
arch_wiki_search/wikis.yaml
arch_wiki_search-20250829.dist-info/METADATA
arch_wiki_search-20250829.dist-info/WHEEL
arch_wiki_search-20250829.dist-info/entry_points.txt
arch_wiki_search-20250829.dist-info/licenses/LICENSE
arch_wiki_search-20250829.dist-info/RECORD
