Metadata-Version: 2.4
Name: arch-wiki-search
Version: 20250829
Summary: Read and search Archwiki and other wikis, online or offline, on the desktop or the terminal
Project-URL: Homepage, https://github.com/clorteau/arch-wiki-search
Project-URL: Issues, https://github.com/clorteau/arch-wiki-search/issues
Author-email: Clem Lorteau <spam@lorteau.fr>
License-Expression: MIT
License-File: LICENSE
Keywords: arch,python,wiki
Classifier: Development Status :: 4 - Beta
Classifier: Environment :: Console
Classifier: Environment :: X11 Applications
Classifier: Framework :: aiohttp
Classifier: Operating System :: OS Independent
Classifier: Programming Language :: Python :: 3
Requires-Python: >=3.6
Requires-Dist: aiodns
Requires-Dist: aiofiles
Requires-Dist: aiohttp
Requires-Dist: aiohttp-client-cache
Requires-Dist: aiosqlite
Requires-Dist: beautifulsoup4
Requires-Dist: html5lib
Requires-Dist: lxml-html-clean
Requires-Dist: markdown
Requires-Dist: markdownify
Requires-Dist: pyyaml
Provides-Extra: gui
Requires-Dist: pyqt6; extra == 'gui'
Provides-Extra: tui
Requires-Dist: textual; extra == 'tui'
